src/bit_stuffer.vhd
library ieee;
  use ieee.std_logic_1164.all;

entity bit_stuffer is
  port (
    clk : in    std_logic;
    rst : in    std_logic;

    -- input data stream
    data_i  : in    std_logic;
    valid_i : in    std_logic;

    -- Output data stream
    stuff_bit_o       : out   std_logic;
    stuff_bit_valid_o : out   std_logic
  );
end entity bit_stuffer;

architecture rtl of bit_stuffer is

  type state_t is (idle, count_1, count_2, count_3, count_4, stuff);

  signal state_reg    : state_t;
  signal last_bit_reg : std_logic;

begin

  -- Synchronous FSM
  p_fsm : process (clk) is
  begin

    if rising_edge(clk) then
      if (rst = '1') then
        state_reg         <= idle;
        last_bit_reg      <= '0';
        stuff_bit_o       <= '0';
        stuff_bit_valid_o <= '0';
      else
        -- Defaults (hold current state/outputs)
        state_reg         <= state_reg;
        last_bit_reg      <= last_bit_reg;
        stuff_bit_o       <= '0';
        stuff_bit_valid_o <= '0';

        if (valid_i = '1') then

          case state_reg is

            when idle =>

              last_bit_reg <= data_i;
              state_reg    <= count_1;

            when count_1 =>

              if (data_i = last_bit_reg) then
                state_reg <= count_2;
              else
                state_reg    <= count_1;
                last_bit_reg <= data_i;
              end if;

            when count_2 =>

              if (data_i = last_bit_reg) then
                state_reg <= count_3;
              else
                state_reg    <= count_1;
                last_bit_reg <= data_i;
              end if;

            when count_3 =>

              if (data_i = last_bit_reg) then
                state_reg <= count_4;
              else
                state_reg    <= count_1;
                last_bit_reg <= data_i;
              end if;

            when count_4 =>

              if (data_i = last_bit_reg) then
                state_reg <= stuff;
              else
                state_reg    <= count_1;
                last_bit_reg <= data_i;
              end if;

            when stuff =>

              stuff_bit_o       <= not last_bit_reg;
              stuff_bit_valid_o <= '1';
              state_reg         <= count_1;
              last_bit_reg      <= data_i;

            when others =>

          end case;

        end if;
      end if;
    end if;

  end process p_fsm;

end architecture rtl;

src/bit_stuffer_fd.vhd
library ieee;
  use ieee.std_logic_1164.all;
  use ieee.numeric_std.all;
  use work.can_package.all;

entity bit_stuffer_fd is
  port (
    bs_fd_i : in    mac_fsm_to_bs_fd_t;
    bs_fd_o : out   bs_fd_to_mac_fsm_t
  );
end entity bit_stuffer_fd;

architecture rtl of bit_stuffer_fd is

  -- Function calculates the parity bit of a std_logic_vector
  function calc_parity (
    v : std_logic_vector
  ) return std_logic is

    variable v_parity : std_logic := '0';

  begin

    for i in v'range loop
      v_parity := v_parity xor v(i);
    end loop;

    return v_parity;

  end function calc_parity;

  -- Function Gray encodes a std_logic_vector
  function to_gray (
    v : std_logic_vector
  ) return std_logic_vector is

    variable result : std_logic_vector(v'range);

  begin

    result(v'left) := v(v'left);

    for i in v'left - 1 downto v'right loop
      result(i) := v(i) xor v(i + 1);
    end loop;

    return result;

  end function to_gray;

  -- Signal declarations
  signal count_reg : unsigned(2 downto 0);
  signal wire      : std_logic;

begin

  -- Encodes the stuff bit count in Gray code with parity bit
  p_stuff_bit_count_encode : process (bs_fd_i.clk) is

    variable v_gray_bits  : std_logic_vector(2 downto 0);
    variable v_parity_bit : std_logic;
    variable v_count_temp : unsigned(2 downto 0);

  begin

    if rising_edge(bs_fd_i.clk) then
      if (bs_fd_i.rst = '1') then
        count_reg    <= (others => '0');
        bs_fd_o.sbc  <= (others => '0');
        v_gray_bits  := (others => '0');
        v_parity_bit := '0';
        v_count_temp := (others => '0');
      else
        if (wire = '1') then
          v_count_temp := count_reg + 1;
          v_gray_bits  := to_gray(std_logic_vector(v_count_temp));       -- Gray code count
          v_parity_bit := calc_parity(v_gray_bits);                      -- Calc parity bit

          -- Update registers
          bs_fd_o.sbc <= v_gray_bits & v_parity_bit;
          count_reg   <= v_count_temp;
        end if;
      end if;
    end if;

  end process p_stuff_bit_count_encode;

  -- Bit stuffer FSM
  u_bit_stuffer : entity work.bit_stuffer
    port map (
      clk               => bs_fd_i.clk,
      rst               => bs_fd_i.rst,
      data_i            => bs_fd_i.data,
      valid_i           => bs_fd_i.data_valid,
      stuff_bit_o       => bs_fd_o.stuff_bit,
      stuff_bit_valid_o => wire
    );

  bs_fd_o.stuff_bit_valid <= wire;

end architecture rtl;

src/bit_stuffer_fd_tb.vhd
library ieee;
use ieee.std_logic_1164.all;
use ieee.numeric_std.all;

library osvvm;
context osvvm.OsvvmContext;

use work.can_package.all;

entity bit_stuffer_fd_tb is
end entity bit_stuffer_fd_tb;

architecture tb of bit_stuffer_fd_tb is

  constant CLK_PERIOD : time := 10 ns;
  constant RUN_TIME : time := 100 us;

  signal clk_i : std_logic := '0';
  signal bs_fd_i : mac_fsm_to_bs_fd_t;
  signal bs_fd_o : bs_fd_to_mac_fsm_t;

  -- Signals for waveform viewing (unpacked from records)
  signal tb_clk : std_logic;
  signal tb_rst : std_logic;
  signal tb_data_i : std_logic;
  signal tb_data_valid : std_logic;
  signal tb_stuff_bit : std_logic;
  signal tb_stuff_bit_valid : std_logic;
  signal tb_sbc : std_logic_vector(3 downto 0);

begin

  -- Clock generation
  clk_i <= not clk_i after CLK_PERIOD / 2;
  bs_fd_i.clk <= clk_i;

  -- Unpack records to signals for waveform viewing
  tb_clk <= bs_fd_i.clk;
  tb_rst <= bs_fd_i.rst;
  tb_data_i <= bs_fd_i.data;
  tb_data_valid <= bs_fd_i.data_valid;
  tb_stuff_bit <= bs_fd_o.stuff_bit;
  tb_stuff_bit_valid <= bs_fd_o.stuff_bit_valid;
  tb_sbc <= bs_fd_o.sbc;

  -- DUT instantiation
  u_dut : entity work.bit_stuffer_fd
    port map (
      bs_fd_i => bs_fd_i,
      bs_fd_o => bs_fd_o
    );

  -- Main test process
  main_tb_p : process
    variable rnd_bit : RandomPType;
    variable rnd_valid : RandomPType;
    variable random_bit : std_logic;
    variable random_valid : boolean;
    variable num_bits : integer;
  begin
    -- Open transcript file for logging
    TranscriptOpen("sim/bit_stuffer_fd_tb.txt");
    SetTranscriptMirror(TRUE);

    Print("=== Bit Stuffer FD Testbench Started ===");

    -- Note: VCD waveform captures all signals automatically.
    -- View with: gtkwave sim/bit_stuffer_fd_tb.vcd
    -- Expand hierarchy to see record fields and internal signals

    -- Initialize random generators with different seeds
    rnd_bit.InitSeed(rnd_bit'instance_name & to_string(now));
    rnd_valid.InitSeed(rnd_valid'instance_name & to_string(now));

    -- Initialize test parameters
    num_bits := 300;  -- Number of bits to send in each test pattern

    -- Reset for a few cycles
    Print("Applying reset...");
    bs_fd_i.rst <= '1';
    bs_fd_i.data_valid <= '0';
    bs_fd_i.data <= '0';
    wait for CLK_PERIOD * 5;

    -- Release reset
    bs_fd_i.rst <= '0';
    wait for CLK_PERIOD;
    Print("Reset released");

    -- Test 1: Send known patterns that trigger bit stuffing (5 consecutive identical bits)
    Print("Sending pattern to trigger bit stuffing: 00000...");
    for i in 0 to 9 loop
      bs_fd_i.data <= '0';
      bs_fd_i.data_valid <= '1';
      wait for CLK_PERIOD;
    end loop;

    Print("Sending pattern: 11111...");
    for i in 0 to 9 loop
      bs_fd_i.data <= '1';
      bs_fd_i.data_valid <= '1';
      wait for CLK_PERIOD;
    end loop;

    -- Test 2: Random bit pattern with random valid signal
    Print("Sending random bit pattern with variable valid timing...");
    for i in 0 to num_bits loop
      random_bit := '0' when rnd_bit.RandInt(0, 1) = 0 else '1';
      random_valid := rnd_valid.RandInt(0, 1) = 0;  -- ~50% chance of valid

      bs_fd_i.data <= random_bit;
      bs_fd_i.data_valid <= '1' when random_valid else '0';
      wait for CLK_PERIOD;
    end loop;

    -- Random burst of valid data
    Print("Sending random burst...");
    for i in 0 to num_bits loop
      random_bit := '0' when rnd_bit.RandInt(0, 1) = 0 else '1';
      bs_fd_i.data <= random_bit;
      bs_fd_i.data_valid <= '1';
      wait for CLK_PERIOD;
    end loop;

    -- Stop and wait for cleanup
    Print("Test complete, waiting for outputs to settle...");
    bs_fd_i.data_valid <= '0';
    wait for CLK_PERIOD * 20;

    Print("=== Bit Stuffer FD Testbench Finished ===");
    TranscriptClose;

    std.env.finish;

  end process main_tb_p;

  -- Simple monitor - display stuff bits and Gray code with parity
  monitor_p : process (clk_i)
    variable output_count : integer := 0;
  begin
    if rising_edge(clk_i) then
      if bs_fd_o.stuff_bit_valid = '1' then
        output_count := output_count + 1;
        Print("Output #" & to_string(output_count) & ": " & to_string(bs_fd_o.stuff_bit) &
              " Gray+Parity=" & to_hstring(bs_fd_o.sbc) &
              " at time " & to_string(now));
      end if;
    end if;
  end process monitor_p;

end architecture tb;

sim/bit_stuffer_fd_tb.vcd
$date
  Mon Feb  2 16:43:23 2026
$end
$version
  GHDL v0
$end
$timescale
  1 fs
$end
$scope module standard $end
$upscope $end
$scope module textio $end
$upscope $end
$scope module std_logic_1164 $end
$upscope $end
$scope module numeric_std $end
$upscope $end
$scope module ifelsepkg $end
$upscope $end
$scope module osvvmtypespkg $end
$upscope $end
$scope module osvvmscriptsettingspkg $end
$upscope $end
$scope module namepkg $end
$upscope $end
$scope module resolutionpkg $end
$upscope $end
$scope module osvvmglobalpkg $end
$upscope $end
$scope module transcriptpkg $end
$upscope $end
$scope module textutilpkg $end
$upscope $end
$scope module fileutilpkg $end
$upscope $end
$scope module osvvmsettingspkg $end
$upscope $end
$scope module languagesupport2019pkg $end
$upscope $end
$scope module alertlogpkg $end
$upscope $end
$scope module env $end
$upscope $end
$scope module namestorepkg $end
$upscope $end
$scope module std_logic_textio $end
$upscope $end
$scope module sortlistpkg_int $end
$upscope $end
$scope module math_real $end
$upscope $end
$scope module tbutilpkg $end
$comment barrier is not handled $end
$upscope $end
$scope module randombasepkg $end
$upscope $end
$scope module numeric_std_unsigned $end
$upscope $end
$scope module randompkg $end
$upscope $end
$scope module randompkg2019 $end
$upscope $end
$scope module randomprocedurepkg $end
$upscope $end
$scope module messagelistpkg $end
$upscope $end
$scope module coveragevendorapipkg $end
$upscope $end
$scope module coveragepkg $end
$upscope $end
$scope module delaycoveragepkg $end
$upscope $end
$scope module memorysupportpkg $end
$upscope $end
$scope module resizepkg $end
$upscope $end
$scope module clockresetpkg $end
$upscope $end
$scope module reportpkg $end
$upscope $end
$scope module filelinepathpkg $end
$upscope $end
$scope module can_package $end
$upscope $end
$scope module bit_stuffer_fd_tb $end
$var reg 1 ! clk_i $end
$comment bs_fd_i is not handled $end
$comment bs_fd_o is not handled $end
$var reg 1 " tb_clk $end
$var reg 1 # tb_rst $end
$var reg 1 $ tb_data_i $end
$var reg 1 % tb_data_valid $end
$var reg 1 & tb_stuff_bit $end
$var reg 1 ' tb_stuff_bit_valid $end
$var reg 4 ( tb_sbc[3:0] $end
$scope module u_dut $end
$comment bs_fd_i is not handled $end
$comment bs_fd_o is not handled $end
$var reg 3 ) count_reg[2:0] $end
$var reg 1 * wire $end
$scope module u_bit_stuffer $end
$var reg 1 + clk $end
$var reg 1 , rst $end
$var reg 1 - data_i $end
$var reg 1 . valid_i $end
$var reg 1 / stuff_bit_o $end
$var reg 1 0 stuff_bit_valid_o $end
$comment state_reg is not handled $end
$var reg 1 1 last_bit_reg $end
$upscope $end
$upscope $end
$upscope $end
$enddefinitions $end
#0
0!
0"
1#
0$
0%
U&
U'
bUUUU (
bUUU )
U*
0+
1,
0-
0.
U/
U0
U1
#5000000
1!
1"
0&
0'
b0000 (
b000 )
0*
1+
0/
00
01
#10000000
0!
0"
0+
#15000000
1!
1"
1+
#20000000
0!
0"
0+
#25000000
1!
1"
1+
#30000000
0!
0"
0+
#35000000
1!
1"
1+
#40000000
0!
0"
0+
#45000000
1!
1"
1+
#50000000
0!
0"
0#
0+
0,
#55000000
1!
1"
1+
#60000000
0!
0"
1%
0+
1.
#65000000
1!
1"
1+
#70000000
0!
0"
0+
#75000000
1!
1"
1+
#80000000
0!
0"
0+
#85000000
1!
1"
1+
#90000000
0!
0"
0+
#95000000
1!
1"
1+
#100000000
0!
0"
0+
#105000000
1!
1"
1+
#110000000
0!
0"
0+
#115000000
1!
1"
1&
1'
1*
1+
1/
10
#120000000
0!
0"
0+
#125000000
1!
1"
0&
0'
b0011 (
b001 )
0*
1+
0/
00
#130000000
0!
0"
0+
#135000000
1!
1"
1+
#140000000
0!
0"
0+
#145000000
1!
1"
1+
#150000000
0!
0"
0+
#155000000
1!
1"
1+
#160000000
0!
0"
1$
0+
1-
#165000000
1!
1"
1&
1'
1*
1+
1/
10
11
#170000000
0!
0"
0+
#175000000
1!
1"
0&
0'
b0110 (
b010 )
0*
1+
0/
00
#180000000
0!
0"
0+
#185000000
1!
1"
1+
#190000000
0!
0"
0+
#195000000
1!
1"
1+
#200000000
0!
0"
0+
#205000000
1!
1"
1+
#210000000
0!
0"
0+
#215000000
1!
1"
1'
1*
1+
10
#220000000
0!
0"
0+
#225000000
1!
1"
0'
b0101 (
b011 )
0*
1+
00
#230000000
0!
0"
0+
#235000000
1!
1"
1+
#240000000
0!
0"
0+
#245000000
1!
1"
1+
#250000000
0!
0"
0+
#255000000
1!
1"
1+
#260000000
0!
0"
0$
0%
0+
0-
0.
#265000000
1!
1"
1+
#270000000
0!
0"
1$
0+
1-
#275000000
1!
1"
1+
#280000000
0!
0"
1%
0+
1.
#285000000
1!
1"
1'
1*
1+
10
#290000000
0!
0"
0+
#295000000
1!
1"
0'
b1100 (
b100 )
0*
1+
00
#300000000
0!
0"
0%
0+
0.
#305000000
1!
1"
1+
#310000000
0!
0"
0+
#315000000
1!
1"
1+
#320000000
0!
0"
1%
0+
1.
#325000000
1!
1"
1+
#330000000
0!
0"
0$
0%
0+
0-
0.
#335000000
1!
1"
1+
#340000000
0!
0"
0+
#345000000
1!
1"
1+
#350000000
0!
0"
1$
1%
0+
1-
1.
#355000000
1!
1"
1+
#360000000
0!
0"
0$
0+
0-
#365000000
1!
1"
1+
01
#370000000
0!
0"
0%
0+
0.
#375000000
1!
1"
1+
#380000000
0!
0"
1%
0+
1.
#385000000
1!
1"
1+
#390000000
0!
0"
1$
0%
0+
1-
0.
#395000000
1!
1"
1+
#400000000
0!
0"
0$
1%
0+
0-
1.
#405000000
1!
1"
1+
#410000000
0!
0"
1$
0%
0+
1-
0.
#415000000
1!
1"
1+
#420000000
0!
0"
1%
0+
1.
#425000000
1!
1"
1+
11
#430000000
0!
0"
0$
0+
0-
#435000000
1!
1"
1+
01
#440000000
0!
0"
1$
0+
1-
#445000000
1!
1"
1+
11
#450000000
0!
0"
0+
#455000000
1!
1"
1+
#460000000
0!
0"
0$
0+
0-
#465000000
1!
1"
1+
01
#470000000
0!
0"
0%
0+
0.
#475000000
1!
1"
1+
#480000000
0!
0"
0+
#485000000
1!
1"
1+
#490000000
0!
0"
0+
#495000000
1!
1"
1+
#500000000
0!
0"
0+
#505000000
1!
1"
1+
#510000000
0!
0"
1$
1%
0+
1-
1.
#515000000
1!
1"
1+
11
#520000000
0!
0"
0+
#525000000
1!
1"
1+
#530000000
0!
0"
0+
#535000000
1!
1"
1+
#540000000
0!
0"
0$
0+
0-
#545000000
1!
1"
1+
01
#550000000
0!
0"
0%
0+
0.
#555000000
1!
1"
1+
#560000000
0!
0"
1$
0+
1-
#565000000
1!
1"
1+
#570000000
0!
0"
0$
0+
0-
#575000000
1!
1"
1+
#580000000
0!
0"
0+
#585000000
1!
1"
1+
#590000000
0!
0"
1%
0+
1.
#595000000
1!
1"
1+
#600000000
0!
0"
0%
0+
0.
#605000000
1!
1"
1+
#610000000
0!
0"
1$
0+
1-
#615000000
1!
1"
1+
#620000000
0!
0"
0$
0+
0-
#625000000
1!
1"
1+
#630000000
0!
0"
1$
0+
1-
#635000000
1!
1"
1+
#640000000
0!
0"
0$
0+
0-
#645000000
1!
1"
1+
#650000000
0!
0"
1$
1%
0+
1-
1.
#655000000
1!
1"
1+
11
#660000000
0!
0"
0%
0+
0.
#665000000
1!
1"
1+
#670000000
0!
0"
0+
#675000000
1!
1"
1+
#680000000
0!
0"
0$
1%
0+
0-
1.
#685000000
1!
1"
1+
01
#690000000
0!
0"
1$
0%
0+
1-
0.
#695000000
1!
1"
1+
#700000000
0!
0"
0$
1%
0+
0-
1.
#705000000
1!
1"
1+
#710000000
0!
0"
1$
0+
1-
#715000000
1!
1"
1+
11
#720000000
0!
0"
0+
#725000000
1!
1"
1+
#730000000
0!
0"
0$
0%
0+
0-
0.
#735000000
1!
1"
1+
#740000000
0!
0"
1$
1%
0+
1-
1.
#745000000
1!
1"
1+
#750000000
0!
0"
0+
#755000000
1!
1"
1+
#760000000
0!
0"
0$
0+
0-
#765000000
1!
1"
1+
01
#770000000
0!
0"
1$
0+
1-
#775000000
1!
1"
1+
11
#780000000
0!
0"
0%
0+
0.
#785000000
1!
1"
1+
#790000000
0!
0"
1%
0+
1.
#795000000
1!
1"
1+
#800000000
0!
0"
0$
0%
0+
0-
0.
#805000000
1!
1"
1+
#810000000
0!
0"
0+
#815000000
1!
1"
1+
#820000000
0!
0"
1$
0+
1-
#825000000
1!
1"
1+
#830000000
0!
0"
0$
1%
0+
0-
1.
#835000000
1!
1"
1+
01
#840000000
0!
0"
0+
#845000000
1!
1"
1+
#850000000
0!
0"
1$
0%
0+
1-
0.
#855000000
1!
1"
1+
#860000000
0!
0"
0$
0+
0-
#865000000
1!
1"
1+
#870000000
0!
0"
1$
0+
1-
#875000000
1!
1"
1+
#880000000
0!
0"
0$
1%
0+
0-
1.
#885000000
1!
1"
1+
#890000000
0!
0"
1$
0+
1-
#895000000
1!
1"
1+
11
#900000000
0!
0"
0$
0+
0-
#905000000
1!
1"
1+
01
#910000000
0!
0"
0%
0+
0.
#915000000
1!
1"
1+
#920000000
0!
0"
1$
1%
0+
1-
1.
#925000000
1!
1"
1+
11
#930000000
0!
0"
0$
0%
0+
0-
0.
#935000000
1!
1"
1+
#940000000
0!
0"
0+
#945000000
1!
1"
1+
#950000000
0!
0"
1$
1%
0+
1-
1.
#955000000
1!
1"
1+
#960000000
0!
0"
0$
0+
0-
#965000000
1!
1"
1+
01
#970000000
0!
0"
0+
#975000000
1!
1"
1+
#980000000
0!
0"
0+
#985000000
1!
1"
1+
#990000000
0!
0"
1$
0+
1-
#995000000
1!
1"
1+
11
#1000000000
0!
0"
0+
#1005000000
1!
1"
1+
#1010000000
0!
0"
0%
0+
0.
#1015000000
1!
1"
1+
#1020000000
0!
0"
0$
0+
0-
#1025000000
1!
1"
1+
#1030000000
0!
0"
1$
1%
0+
1-
1.
#1035000000
1!
1"
1+
#1040000000
0!
0"
0$
0+
0-
#1045000000
1!
1"
1+
01
#1050000000
0!
0"
1$
0%
0+
1-
0.
#1055000000
1!
1"
1+
#1060000000
0!
0"
0$
1%
0+
0-
1.
#1065000000
1!
1"
1+
#1070000000
0!
0"
0+
#1075000000
1!
1"
1+
#1080000000
0!
0"
1$
0%
0+
1-
0.
#1085000000
1!
1"
1+
#1090000000
0!
0"
1%
0+
1.
#1095000000
1!
1"
1+
11
#1100000000
0!
0"
0$
0%
0+
0-
0.
#1105000000
1!
1"
1+
#1110000000
0!
0"
1$
1%
0+
1-
1.
#1115000000
1!
1"
1+
#1120000000
0!
0"
0$
0%
0+
0-
0.
#1125000000
1!
1"
1+
#1130000000
0!
0"
0+
#1135000000
1!
1"
1+
#1140000000
0!
0"
1$
1%
0+
1-
1.
#1145000000
1!
1"
1+
#1150000000
0!
0"
0$
0+
0-
#1155000000
1!
1"
1+
01
#1160000000
0!
0"
0%
0+
0.
#1165000000
1!
1"
1+
#1170000000
0!
0"
0+
#1175000000
1!
1"
1+
#1180000000
0!
0"
0+
#1185000000
1!
1"
1+
#1190000000
0!
0"
1$
0+
1-
#1195000000
1!
1"
1+
#1200000000
0!
0"
1%
0+
1.
#1205000000
1!
1"
1+
11
#1210000000
0!
0"
0%
0+
0.
#1215000000
1!
1"
1+
#1220000000
0!
0"
0$
1%
0+
0-
1.
#1225000000
1!
1"
1+
01
#1230000000
0!
0"
1$
0+
1-
#1235000000
1!
1"
1+
11
#1240000000
0!
0"
0$
0%
0+
0-
0.
#1245000000
1!
1"
1+
#1250000000
0!
0"
0+
#1255000000
1!
1"
1+
#1260000000
0!
0"
1$
0+
1-
#1265000000
1!
1"
1+
#1270000000
0!
0"
0+
#1275000000
1!
1"
1+
#1280000000
0!
0"
0$
1%
0+
0-
1.
#1285000000
1!
1"
1+
01
#1290000000
0!
0"
1$
0%
0+
1-
0.
#1295000000
1!
1"
1+
#1300000000
0!
0"
0$
1%
0+
0-
1.
#1305000000
1!
1"
1+
#1310000000
0!
0"
0+
#1315000000
1!
1"
1+
#1320000000
0!
0"
0+
#1325000000
1!
1"
1+
#1330000000
0!
0"
0+
#1335000000
1!
1"
1+
#1340000000
0!
0"
1$
0+
1-
#1345000000
1!
1"
1&
1'
1*
1+
1/
10
11
#1350000000
0!
0"
0$
0%
0+
0-
0.
#1355000000
1!
1"
0&
0'
b1111 (
b101 )
0*
1+
0/
00
#1360000000
0!
0"
1$
1%
0+
1-
1.
#1365000000
1!
1"
1+
#1370000000
0!
0"
0$
0+
0-
#1375000000
1!
1"
1+
01
#1380000000
0!
0"
0%
0+
0.
#1385000000
1!
1"
1+
#1390000000
0!
0"
1%
0+
1.
#1395000000
1!
1"
1+
#1400000000
0!
0"
0+
#1405000000
1!
1"
1+
#1410000000
0!
0"
1$
0+
1-
#1415000000
1!
1"
1+
11
#1420000000
0!
0"
0%
0+
0.
#1425000000
1!
1"
1+
#1430000000
0!
0"
0$
1%
0+
0-
1.
#1435000000
1!
1"
1+
01
#1440000000
0!
0"
1$
0+
1-
#1445000000
1!
1"
1+
11
#1450000000
0!
0"
0$
0%
0+
0-
0.
#1455000000
1!
1"
1+
#1460000000
0!
0"
1%
0+
1.
#1465000000
1!
1"
1+
01
#1470000000
0!
0"
1$
0+
1-
#1475000000
1!
1"
1+
11
#1480000000
0!
0"
0$
0+
0-
#1485000000
1!
1"
1+
01
#1490000000
0!
0"
0+
#1495000000
1!
1"
1+
#1500000000
0!
0"
0+
#1505000000
1!
1"
1+
#1510000000
0!
0"
0+
#1515000000
1!
1"
1+
#1520000000
0!
0"
1$
0%
0+
1-
0.
#1525000000
1!
1"
1+
#1530000000
0!
0"
1%
0+
1.
#1535000000
1!
1"
1+
11
#1540000000
0!
0"
0+
#1545000000
1!
1"
1+
#1550000000
0!
0"
0%
0+
0.
#1555000000
1!
1"
1+
#1560000000
0!
0"
0+
#1565000000
1!
1"
1+
#1570000000
0!
0"
1%
0+
1.
#1575000000
1!
1"
1+
#1580000000
0!
0"
0%
0+
0.
#1585000000
1!
1"
1+
#1590000000
0!
0"
1%
0+
1.
#1595000000
1!
1"
1+
#1600000000
0!
0"
0+
#1605000000
1!
1"
1+
#1610000000
0!
0"
0$
0+
0-
#1615000000
1!
1"
1'
1*
1+
10
01
#1620000000
0!
0"
0+
#1625000000
1!
1"
0'
b1010 (
b110 )
0*
1+
00
#1630000000
0!
0"
1$
0%
0+
1-
0.
#1635000000
1!
1"
1+
#1640000000
0!
0"
0+
#1645000000
1!
1"
1+
#1650000000
0!
0"
1%
0+
1.
#1655000000
1!
1"
1+
11
#1660000000
0!
0"
0%
0+
0.
#1665000000
1!
1"
1+
#1670000000
0!
0"
0$
0+
0-
#1675000000
1!
1"
1+
#1680000000
0!
0"
0+
#1685000000
1!
1"
1+
#1690000000
0!
0"
1$
1%
0+
1-
1.
#1695000000
1!
1"
1+
#1700000000
0!
0"
0%
0+
0.
#1705000000
1!
1"
1+
#1710000000
0!
0"
0+
#1715000000
1!
1"
1+
#1720000000
0!
0"
0$
1%
0+
0-
1.
#1725000000
1!
1"
1+
01
#1730000000
0!
0"
0%
0+
0.
#1735000000
1!
1"
1+
#1740000000
0!
0"
0+
#1745000000
1!
1"
1+
#1750000000
0!
0"
1%
0+
1.
#1755000000
1!
1"
1+
#1760000000
0!
0"
0%
0+
0.
#1765000000
1!
1"
1+
#1770000000
0!
0"
0+
#1775000000
1!
1"
1+
#1780000000
0!
0"
1$
1%
0+
1-
1.
#1785000000
1!
1"
1+
11
#1790000000
0!
0"
0$
0+
0-
#1795000000
1!
1"
1+
01
#1800000000
0!
0"
1$
0+
1-
#1805000000
1!
1"
1+
11
#1810000000
0!
0"
0%
0+
0.
#1815000000
1!
1"
1+
#1820000000
0!
0"
1%
0+
1.
#1825000000
1!
1"
1+
#1830000000
0!
0"
0$
0+
0-
#1835000000
1!
1"
1+
01
#1840000000
0!
0"
0+
#1845000000
1!
1"
1+
#1850000000
0!
0"
1$
0+
1-
#1855000000
1!
1"
1+
11
#1860000000
0!
0"
0+
#1865000000
1!
1"
1+
#1870000000
0!
0"
0%
0+
0.
#1875000000
1!
1"
1+
#1880000000
0!
0"
1%
0+
1.
#1885000000
1!
1"
1+
#1890000000
0!
0"
0$
0+
0-
#1895000000
1!
1"
1+
01
#1900000000
0!
0"
0+
#1905000000
1!
1"
1+
#1910000000
0!
0"
1$
0%
0+
1-
0.
#1915000000
1!
1"
1+
#1920000000
0!
0"
0+
#1925000000
1!
1"
1+
#1930000000
0!
0"
1%
0+
1.
#1935000000
1!
1"
1+
11
#1940000000
0!
0"
0$
0%
0+
0-
0.
#1945000000
1!
1"
1+
#1950000000
0!
0"
1$
0+
1-
#1955000000
1!
1"
1+
#1960000000
0!
0"
0$
0+
0-
#1965000000
1!
1"
1+
#1970000000
0!
0"
1$
0+
1-
#1975000000
1!
1"
1+
#1980000000
0!
0"
0$
1%
0+
0-
1.
#1985000000
1!
1"
1+
01
#1990000000
0!
0"
1$
0%
0+
1-
0.
#1995000000
1!
1"
1+
#2000000000
0!
0"
0+
#2005000000
1!
1"
1+
#2010000000
0!
0"
0$
1%
0+
0-
1.
#2015000000
1!
1"
1+
#2020000000
0!
0"
1$
0%
0+
1-
0.
#2025000000
1!
1"
1+
#2030000000
0!
0"
0$
1%
0+
0-
1.
#2035000000
1!
1"
1+
#2040000000
0!
0"
1$
0%
0+
1-
0.
#2045000000
1!
1"
1+
#2050000000
0!
0"
0$
1%
0+
0-
1.
#2055000000
1!
1"
1+
#2060000000
0!
0"
1$
0+
1-
#2065000000
1!
1"
1+
11
#2070000000
0!
0"
0$
0+
0-
#2075000000
1!
1"
1+
01
#2080000000
0!
0"
0+
#2085000000
1!
1"
1+
#2090000000
0!
0"
0+
#2095000000
1!
1"
1+
#2100000000
0!
0"
1$
0%
0+
1-
0.
#2105000000
1!
1"
1+
#2110000000
0!
0"
0$
1%
0+
0-
1.
#2115000000
1!
1"
1+
#2120000000
0!
0"
1$
0+
1-
#2125000000
1!
1"
1+
11
#2130000000
0!
0"
0$
0+
0-
#2135000000
1!
1"
1+
01
#2140000000
0!
0"
0%
0+
0.
#2145000000
1!
1"
1+
#2150000000
0!
0"
1$
1%
0+
1-
1.
#2155000000
1!
1"
1+
11
#2160000000
0!
0"
0%
0+
0.
#2165000000
1!
1"
1+
#2170000000
0!
0"
0$
1%
0+
0-
1.
#2175000000
1!
1"
1+
01
#2180000000
0!
0"
1$
0%
0+
1-
0.
#2185000000
1!
1"
1+
#2190000000
0!
0"
1%
0+
1.
#2195000000
1!
1"
1+
11
#2200000000
0!
0"
0%
0+
0.
#2205000000
1!
1"
1+
#2210000000
0!
0"
0+
#2215000000
1!
1"
1+
#2220000000
0!
0"
1%
0+
1.
#2225000000
1!
1"
1+
#2230000000
0!
0"
0+
#2235000000
1!
1"
1+
#2240000000
0!
0"
0%
0+
0.
#2245000000
1!
1"
1+
#2250000000
0!
0"
0$
0+
0-
#2255000000
1!
1"
1+
#2260000000
0!
0"
0+
#2265000000
1!
1"
1+
#2270000000
0!
0"
1$
0+
1-
#2275000000
1!
1"
1+
#2280000000
0!
0"
1%
0+
1.
#2285000000
1!
1"
1+
#2290000000
0!
0"
0$
0%
0+
0-
0.
#2295000000
1!
1"
1+
#2300000000
0!
0"
0+
#2305000000
1!
1"
1+
#2310000000
0!
0"
0+
#2315000000
1!
1"
1+
#2320000000
0!
0"
0+
#2325000000
1!
1"
1+
#2330000000
0!
0"
0+
#2335000000
1!
1"
1+
#2340000000
0!
0"
1%
0+
1.
#2345000000
1!
1"
1+
01
#2350000000
0!
0"
1$
0+
1-
#2355000000
1!
1"
1+
11
#2360000000
0!
0"
0%
0+
0.
#2365000000
1!
1"
1+
#2370000000
0!
0"
0$
0+
0-
#2375000000
1!
1"
1+
#2380000000
0!
0"
1%
0+
1.
#2385000000
1!
1"
1+
01
#2390000000
0!
0"
1$
0%
0+
1-
0.
#2395000000
1!
1"
1+
#2400000000
0!
0"
0$
1%
0+
0-
1.
#2405000000
1!
1"
1+
#2410000000
0!
0"
0+
#2415000000
1!
1"
1+
#2420000000
0!
0"
0%
0+
0.
#2425000000
1!
1"
1+
#2430000000
0!
0"
1$
0+
1-
#2435000000
1!
1"
1+
#2440000000
0!
0"
0+
#2445000000
1!
1"
1+
#2450000000
0!
0"
0$
1%
0+
0-
1.
#2455000000
1!
1"
1+
#2460000000
0!
0"
1$
0%
0+
1-
0.
#2465000000
1!
1"
1+
#2470000000
0!
0"
0$
1%
0+
0-
1.
#2475000000
1!
1"
1+
#2480000000
0!
0"
1$
0+
1-
#2485000000
1!
1"
1&
1'
1*
1+
1/
10
11
#2490000000
0!
0"
0$
0+
0-
#2495000000
1!
1"
0&
0'
b1001 (
b111 )
0*
1+
0/
00
01
#2500000000
0!
0"
0+
#2505000000
1!
1"
1+
#2510000000
0!
0"
1$
0+
1-
#2515000000
1!
1"
1+
11
#2520000000
0!
0"
0$
0%
0+
0-
0.
#2525000000
1!
1"
1+
#2530000000
0!
0"
0+
#2535000000
1!
1"
1+
#2540000000
0!
0"
1%
0+
1.
#2545000000
1!
1"
1+
01
#2550000000
0!
0"
1$
0+
1-
#2555000000
1!
1"
1+
11
#2560000000
0!
0"
0%
0+
0.
#2565000000
1!
1"
1+
#2570000000
0!
0"
0$
0+
0-
#2575000000
1!
1"
1+
#2580000000
0!
0"
1$
0+
1-
#2585000000
1!
1"
1+
