src/bit_stuffer.vhd
library ieee;
  use ieee.std_logic_1164.all;

entity bit_stuffer is
  port (
    clk : in    std_logic;
    rst : in    std_logic;

    -- input data stream
    data_i  : in    std_logic;
    valid_i : in    std_logic;

    -- Output data stream
    stuff_bit_o       : out   std_logic;
    stuff_bit_valid_o : out   std_logic
  );
end entity bit_stuffer;

architecture rtl of bit_stuffer is

  type state_t is (idle, count_1, count_2, count_3,  count_4, stuff);

  signal state_reg,    state_next    : state_t;
  signal last_bit_reg, last_bit_next : std_logic;

begin

  -- State register
  p_state_update : process (clk) is
  begin

    if rising_edge(clk) then
      if (rst = '1') then
        state_reg    <= idle;
        last_bit_reg <= '0';
      else
        state_reg    <= state_next;
        last_bit_reg <= last_bit_next;
      end if;
    end if;

  end process p_state_update;

  p_next_state_and_output_logic : process (all) is
  begin

    -- Defaults
    state_next        <= state_reg;
    last_bit_next     <= last_bit_reg;
    stuff_bit_o       <= '0';
    stuff_bit_valid_o <= '0';

    if (valid_i = '1') then
      case state_reg is
        when idle =>
          last_bit_next <= data_i;
          state_next    <= count_1;

        when count_1 =>
          if (data_i = last_bit_reg) then
            state_next <= count_2;
          else
            state_next    <= count_1;
            last_bit_next <= data_i;
          end if;

        when count_2 =>
          if (data_i = last_bit_reg) then
            state_next <= count_3;
          else
            state_next    <= count_1;
            last_bit_next <= data_i;
          end if;

        when count_3 =>
          if (data_i = last_bit_reg) then
            state_next <= count_4;
          else
            state_next    <= count_1;
            last_bit_next <= data_i;
          end if;

        when count_4 =>
          if (data_i = last_bit_reg) then
            state_next <= stuff;
          else
            state_next    <= count_1;
            last_bit_next <= data_i;
          end if;

        when stuff =>
          stuff_bit_o       <= not last_bit_reg;
          stuff_bit_valid_o <= '1';

          state_next    <= count_1;
          last_bit_next <= data_i;
        when others =>

      end case;
    end if;

  end process p_next_state_and_output_logic;

end architecture rtl;

src/bit_stuffer_fd.vhd
library ieee;
  use ieee.std_logic_1164.all;
  use ieee.numeric_std.all;

entity bit_stuffer_fd is
  port (
    clk : in    std_logic;
    rst : in    std_logic;

    -- input data stream
    data_i  : in    std_logic;
    valid_i : in    std_logic;

    -- Output data stream
    stuff_bit_o       : out   std_logic;
    stuff_bit_valid_o : out   std_logic;
    bsc_and_parity_o  : out   std_logic_vector(3 downto 0)
  );
end entity bit_stuffer_fd;

architecture rtl of bit_stuffer_fd is

  -- Function calculates the parity bit of a std_logic_vector

  function calc_parity (
    v : std_logic_vector
  ) return std_logic is

    variable v_parity : std_logic := '0';

  begin

    for i in v'range loop

      v_parity := v_parity xor v(i);

    end loop;

    return v_parity;

  end function calc_parity;

  -- Function Gray encodes a std_logic_vector

  function to_gray (
    v : std_logic_vector
  ) return std_logic_vector is

    variable result : std_logic_vector(v'range);

  begin

    result(v'left) := v(v'left);

    for i in v'left - 1 downto v'right loop

      result(i) := v(i) xor v(i + 1);

    end loop;

    return result;

  end function to_gray;

  signal count_reg : unsigned(2 downto 0);
  signal wire      : std_logic;

begin

  -- Encodes the stuff bit count in Gray code with parity bit
  p_stuff_bit_count_encode : process (clk) is

    variable v_gray_bits  : std_logic_vector(2 downto 0);
    variable v_parity_bit : std_logic;
    variable v_count_temp : unsigned(2 downto 0);

  begin

    if rising_edge(clk) then
      if (rst = '1') then
        count_reg        <= (others => '0');
        bsc_and_parity_o <= (others => '0');
        v_gray_bits      := (others => '0');
        v_parity_bit     := '0';
        v_count_temp     := (others => '0');
      else
        if (wire = '1') then
          v_count_temp := count_reg + 1;
          v_gray_bits  := to_gray(std_logic_vector(v_count_temp));       -- Gray code count
          v_parity_bit := calc_parity(v_gray_bits);                      -- Calc parity bit

          -- Update registers
          bsc_and_parity_o <= v_gray_bits & v_parity_bit;
          count_reg        <= v_count_temp;
        end if;
      end if;
    end if;

  end process p_stuff_bit_count_encode;

  -- Bit stuffer FSM
  u_bit_stuffer : entity work.bit_stuffer
    port map (
      clk               => clk,
      rst               => rst,
      data_i            => data_i,
      valid_i           => valid_i,
      stuff_bit_o       => stuff_bit_o,
      stuff_bit_valid_o => wire
    );

  stuff_bit_valid_o <= wire;

end architecture rtl;

src/bit_stuffer_fd_tb.vhd
library ieee;
use ieee.std_logic_1164.all;
use ieee.numeric_std.all;

library osvvm;
context osvvm.OsvvmContext;

entity bit_stuffer_fd_tb is
end entity bit_stuffer_fd_tb;

architecture tb of bit_stuffer_fd_tb is

  constant CLK_PERIOD : time := 10 ns;
  constant RUN_TIME : time := 100 us;

  signal clk_i   : std_logic := '0';
  signal rst_i   : std_logic := '1';
  signal valid_i : std_logic := '0';
  signal data_i  : std_logic := '0';
  signal stuff_bit_o  : std_logic;
  signal stuff_bit_valid_o : std_logic;
  signal bsc_and_parity_o : std_logic_vector(3 downto 0);

begin

  -- Clock generation
  clk_i <= not clk_i after CLK_PERIOD / 2;

  -- DUT instantiation
  u_dut : entity work.bit_stuffer_fd
    port map (
      clk   => clk_i,
      rst   => rst_i,
      data_i  => data_i,
      valid_i => valid_i,
      stuff_bit_o  => stuff_bit_o,
      stuff_bit_valid_o => stuff_bit_valid_o,
      bsc_and_parity_o => bsc_and_parity_o
    );

  -- Main test process
  main_tb_p : process
    variable rnd_bit : RandomPType;
    variable rnd_valid : RandomPType;
    variable random_bit : std_logic;
    variable random_valid : boolean;
    variable num_bits : integer;
  begin
    -- Open transcript file for logging
    TranscriptOpen("sim/bit_stuffer_fd_tb.txt");
    SetTranscriptMirror(TRUE);

    Print("=== Bit Stuffer FD Testbench Started ===");

    -- Initialize random generators with different seeds
    rnd_bit.InitSeed(rnd_bit'instance_name & to_string(now));
    rnd_valid.InitSeed(rnd_valid'instance_name & to_string(now));

    -- Reset for a few cycles
    Print("Applying reset...");
    rst_i <= '1';
    valid_i <= '0';
    data_i <= '0';
    wait for CLK_PERIOD * 5;

    -- Release reset
    rst_i <= '0';
    wait for CLK_PERIOD;
    Print("Reset released");

    -- Random bit pattern with random valid signal
    Print("Sending random bit pattern with variable valid timing...");
    for i in 0 to num_bits loop
      random_bit := '0' when rnd_bit.RandInt(0, 1) = 0 else '1';
      random_valid := rnd_valid.RandInt(0, 1) = 0;  -- ~50% chance of valid

      data_i <= random_bit;
      valid_i <= '1' when random_valid else '0';
      wait for CLK_PERIOD;
    end loop;

    -- Random burst of valid data
    Print("Sending random burst...");
    for i in 0 to num_bits loop
      random_bit := '0' when rnd_bit.RandInt(0, 1) = 0 else '1';
      data_i <= random_bit;
      valid_i <= '1';
      wait for CLK_PERIOD;
    end loop;

    -- Stop and wait for cleanup
    Print("Test complete, waiting for outputs to settle...");
    valid_i <= '0';
    wait for CLK_PERIOD * 20;

    Print("=== Bit Stuffer FD Testbench Finished ===");
    TranscriptClose;

    std.env.finish;

  end process main_tb_p;

  -- Simple monitor - display stuff bits and Gray code with parity
  monitor_p : process (clk_i)
    variable output_count : integer := 0;
  begin
    if rising_edge(clk_i) then
      if stuff_bit_valid_o = '1' then
        output_count := output_count + 1;
        Print("Output #" & to_string(output_count) & ": " & to_string(stuff_bit_o) &
              " Gray+Parity=" & to_hstring(bsc_and_parity_o) &
              " at time " & to_string(now));
      end if;
    end if;
  end process monitor_p;

end architecture tb;

sim/bit_stuffer_fd_tb.vcd
$date
  Mon Feb  2 11:34:48 2026
$end
$version
  GHDL v0
$end
$timescale
  1 fs
$end
$scope module standard $end
$upscope $end
$scope module textio $end
$upscope $end
$scope module std_logic_1164 $end
$upscope $end
$scope module numeric_std $end
$upscope $end
$scope module ifelsepkg $end
$upscope $end
$scope module osvvmtypespkg $end
$upscope $end
$scope module osvvmscriptsettingspkg $end
$upscope $end
$scope module namepkg $end
$upscope $end
$scope module resolutionpkg $end
$upscope $end
$scope module osvvmglobalpkg $end
$upscope $end
$scope module transcriptpkg $end
$upscope $end
$scope module textutilpkg $end
$upscope $end
$scope module fileutilpkg $end
$upscope $end
$scope module osvvmsettingspkg $end
$upscope $end
$scope module languagesupport2019pkg $end
$upscope $end
$scope module alertlogpkg $end
$upscope $end
$scope module env $end
$upscope $end
$scope module namestorepkg $end
$upscope $end
$scope module std_logic_textio $end
$upscope $end
$scope module sortlistpkg_int $end
$upscope $end
$scope module math_real $end
$upscope $end
$scope module tbutilpkg $end
$comment barrier is not handled $end
$upscope $end
$scope module randombasepkg $end
$upscope $end
$scope module numeric_std_unsigned $end
$upscope $end
$scope module randompkg $end
$upscope $end
$scope module randompkg2019 $end
$upscope $end
$scope module randomprocedurepkg $end
$upscope $end
$scope module messagelistpkg $end
$upscope $end
$scope module coveragevendorapipkg $end
$upscope $end
$scope module coveragepkg $end
$upscope $end
$scope module delaycoveragepkg $end
$upscope $end
$scope module memorysupportpkg $end
$upscope $end
$scope module resizepkg $end
$upscope $end
$scope module clockresetpkg $end
$upscope $end
$scope module reportpkg $end
$upscope $end
$scope module filelinepathpkg $end
$upscope $end
$scope module bit_stuffer_fd_tb $end
$var reg 1 ! clk_i $end
$var reg 1 " rst_i $end
$var reg 1 # valid_i $end
$var reg 1 $ data_i $end
$var reg 1 % stuff_bit_o $end
$var reg 1 & stuff_bit_valid_o $end
$var reg 4 ' bsc_and_parity_o[3:0] $end
$scope module u_dut $end
$var reg 1 ( clk $end
$var reg 1 ) rst $end
$var reg 1 * data_i $end
$var reg 1 + valid_i $end
$var reg 1 , stuff_bit_o $end
$var reg 1 - stuff_bit_valid_o $end
$var reg 4 . bsc_and_parity_o[3:0] $end
$var reg 3 / count_reg[2:0] $end
$var reg 1 0 wire $end
$scope module u_bit_stuffer $end
$var reg 1 1 clk $end
$var reg 1 2 rst $end
$var reg 1 3 data_i $end
$var reg 1 4 valid_i $end
$var reg 1 5 stuff_bit_o $end
$var reg 1 6 stuff_bit_valid_o $end
$comment state_reg is not handled $end
$comment state_next is not handled $end
$var reg 1 7 last_bit_reg $end
$var reg 1 8 last_bit_next $end
$upscope $end
$upscope $end
$upscope $end
$enddefinitions $end
#0
0!
1"
0#
0$
0%
0&
bUUUU '
0(
1)
0*
0+
0,
0-
bUUUU .
bUUU /
00
01
12
03
04
05
06
U7
U8
#5000000
1!
b0000 '
1(
b0000 .
b000 /
11
07
08
#10000000
0!
0(
01
#15000000
1!
1(
11
#20000000
0!
0(
01
#25000000
1!
1(
11
#30000000
0!
0(
01
#35000000
1!
1(
11
#40000000
0!
0(
01
#45000000
1!
1(
11
#50000000
0!
0"
0(
0)
01
02
#55000000
1!
1(
11
#60000000
0!
0(
01
#65000000
1!
1(
11
#70000000
0!
1$
0(
1*
01
13
#75000000
1!
1(
11
#80000000
0!
1#
0(
1+
01
14
18
#85000000
1!
1(
11
17
#90000000
0!
0(
01
#95000000
1!
1(
11
#100000000
0!
0#
0(
0+
01
04
#105000000
1!
1(
11
#110000000
0!
0(
01
#115000000
1!
1(
11
#120000000
0!
1#
0(
1+
01
14
#125000000
1!
1(
11
#130000000
0!
0#
0$
0(
0*
0+
01
03
04
#135000000
1!
1(
11
#140000000
0!
0(
01
#145000000
1!
1(
11
#150000000
0!
1#
1$
0(
1*
1+
01
13
14
#155000000
1!
1(
11
#160000000
0!
0$
0(
0*
01
03
08
#165000000
1!
1(
11
07
#170000000
0!
0#
0(
0+
01
04
#175000000
1!
1(
11
#180000000
0!
1#
0(
1+
01
14
#185000000
1!
1(
11
#190000000
0!
0#
1$
0(
1*
0+
01
13
04
#195000000
1!
1(
11
#200000000
0!
1#
0$
0(
0*
1+
01
03
14
#205000000
1!
1(
11
#210000000
0!
0#
1$
0(
1*
0+
01
13
04
#215000000
1!
1(
11
#220000000
0!
1#
0(
1+
01
14
18
#225000000
1!
1(
11
17
#230000000
0!
0$
0(
0*
01
03
08
#235000000
1!
1(
11
07
#240000000
0!
1$
0(
1*
01
13
18
#245000000
1!
1(
11
17
#250000000
0!
0(
01
#255000000
1!
1(
11
#260000000
0!
0$
0(
0*
01
03
08
#265000000
1!
1(
11
07
#270000000
0!
0#
0(
0+
01
04
#275000000
1!
1(
11
#280000000
0!
0(
01
#285000000
1!
1(
11
#290000000
0!
0(
01
#295000000
1!
1(
11
#300000000
0!
0(
01
#305000000
1!
1(
11
#310000000
0!
1#
1$
0(
1*
1+
01
13
14
18
#315000000
1!
1(
11
17
#320000000
0!
0(
01
#325000000
1!
1(
11
#330000000
0!
0(
01
#335000000
1!
1(
11
#340000000
0!
0$
0(
0*
01
03
08
#345000000
1!
1(
11
07
#350000000
0!
0#
0(
0+
01
04
#355000000
1!
1(
11
#360000000
0!
1$
0(
1*
01
13
#365000000
1!
1(
11
#370000000
0!
0$
0(
0*
01
03
#375000000
1!
1(
11
#380000000
0!
0(
01
#385000000
1!
1(
11
#390000000
0!
1#
0(
1+
01
14
#395000000
1!
1(
11
#400000000
0!
0#
0(
0+
01
04
#405000000
1!
1(
11
#410000000
0!
1$
0(
1*
01
13
#415000000
1!
1(
11
#420000000
0!
0$
0(
0*
01
03
#425000000
1!
1(
11
#430000000
0!
1$
0(
1*
01
13
#435000000
1!
1(
11
#440000000
0!
0$
0(
0*
01
03
#445000000
1!
1(
11
#450000000
0!
1#
1$
0(
1*
1+
01
13
14
18
#455000000
1!
1(
11
17
#460000000
0!
0#
0(
0+
01
04
#465000000
1!
1(
11
#470000000
0!
0(
01
#475000000
1!
1(
11
#480000000
0!
1#
0$
0(
0*
1+
01
03
14
08
#485000000
1!
1(
11
07
#490000000
0!
0#
1$
0(
1*
0+
01
13
04
#495000000
1!
1(
11
#500000000
0!
1#
0$
0(
0*
1+
01
03
14
#505000000
1!
1(
11
#510000000
0!
1$
0(
1*
01
13
18
#515000000
1!
1(
11
17
#520000000
0!
0(
01
#525000000
1!
1(
11
#530000000
0!
0#
0$
0(
0*
0+
01
03
04
#535000000
1!
1(
11
#540000000
0!
1#
1$
0(
1*
1+
01
13
14
#545000000
1!
1(
11
#550000000
0!
0(
01
#555000000
1!
1(
11
#560000000
0!
0$
0(
0*
01
03
08
#565000000
1!
1(
11
07
#570000000
0!
1$
0(
1*
01
13
18
#575000000
1!
1(
11
17
#580000000
0!
0#
0(
0+
01
04
#585000000
1!
1(
11
#590000000
0!
1#
0(
1+
01
14
#595000000
1!
1(
11
#600000000
0!
0#
0$
0(
0*
0+
01
03
04
#605000000
1!
1(
11
#610000000
0!
0(
01
#615000000
1!
1(
11
#620000000
0!
1$
0(
1*
01
13
#625000000
1!
1(
11
#630000000
0!
1#
0$
0(
0*
1+
01
03
14
08
#635000000
1!
1(
11
07
#640000000
0!
0(
01
#645000000
1!
1(
11
#650000000
0!
0#
1$
0(
1*
0+
01
13
04
#655000000
1!
1(
11
#660000000
0!
0$
0(
0*
01
03
#665000000
1!
1(
11
#670000000
0!
1$
0(
1*
01
13
#675000000
1!
1(
11
#680000000
0!
1#
0$
0(
0*
1+
01
03
14
#685000000
1!
1(
11
#690000000
0!
1$
0(
1*
01
13
18
#695000000
1!
1(
11
17
#700000000
0!
0$
0(
0*
01
03
08
#705000000
1!
1(
11
07
#710000000
0!
0#
0(
0+
01
04
#715000000
1!
1(
11
#720000000
0!
1#
1$
0(
1*
1+
01
13
14
18
#725000000
1!
1(
11
17
#730000000
0!
0#
0$
0(
0*
0+
01
03
04
#735000000
1!
1(
11
#740000000
0!
0(
01
#745000000
1!
1(
11
#750000000
0!
1#
1$
0(
1*
1+
01
13
14
#755000000
1!
1(
11
#760000000
0!
0$
0(
0*
01
03
08
#765000000
1!
1(
11
07
#770000000
0!
0(
01
#775000000
1!
1(
11
#780000000
0!
0(
01
#785000000
1!
1(
11
#790000000
0!
1$
0(
1*
01
13
18
#795000000
1!
1(
11
17
#800000000
0!
0(
01
#805000000
1!
1(
11
#810000000
0!
0#
0(
0+
01
04
#815000000
1!
1(
11
#820000000
0!
0$
0(
0*
01
03
#825000000
1!
1(
11
#830000000
0!
1#
1$
0(
1*
1+
01
13
14
#835000000
1!
1(
11
#840000000
0!
0$
0(
0*
01
03
08
#845000000
1!
1(
11
07
#850000000
0!
0#
1$
0(
1*
0+
01
13
04
#855000000
1!
1(
11
#860000000
0!
1#
0$
0(
0*
1+
01
03
14
#865000000
1!
1(
11
#870000000
0!
0(
01
#875000000
1!
1(
11
#880000000
0!
0#
1$
0(
1*
0+
01
13
04
#885000000
1!
1(
11
#890000000
0!
1#
0(
1+
01
14
18
#895000000
1!
1(
11
17
#900000000
0!
0#
0$
0(
0*
0+
01
03
04
#905000000
1!
1(
11
#910000000
0!
1#
1$
0(
1*
1+
01
13
14
#915000000
1!
1(
11
#920000000
0!
0#
0$
0(
0*
0+
01
03
04
#925000000
1!
1(
11
#930000000
0!
0(
01
#935000000
1!
1(
11
#940000000
0!
1#
1$
0(
1*
1+
01
13
14
#945000000
1!
1(
11
#950000000
0!
0$
0(
0*
01
03
08
#955000000
1!
1(
11
07
#960000000
0!
0#
0(
0+
01
04
#965000000
1!
1(
11
#970000000
0!
0(
01
#975000000
1!
1(
11
#980000000
0!
0(
01
#985000000
1!
1(
11
#990000000
0!
1$
0(
1*
01
13
#995000000
1!
1(
11
#1000000000
0!
1#
0(
1+
01
14
18
#1005000000
1!
1(
11
17
#1010000000
0!
0#
0(
0+
01
04
#1015000000
1!
1(
11
#1020000000
0!
1#
0$
0(
0*
1+
01
03
14
08
#1025000000
1!
1(
11
07
#1030000000
0!
1$
0(
1*
01
13
18
#1035000000
1!
1(
11
17
#1040000000
0!
0#
0$
0(
0*
0+
01
03
04
#1045000000
1!
1(
11
#1050000000
0!
0(
01
#1055000000
1!
1(
11
#1060000000
0!
1$
0(
1*
01
13
#1065000000
1!
1(
11
#1070000000
0!
0(
01
#1075000000
1!
1(
11
#1080000000
0!
1#
0$
0(
0*
1+
01
03
14
08
#1085000000
1!
1(
11
07
#1090000000
0!
0#
1$
0(
1*
0+
01
13
04
#1095000000
1!
1(
11
#1100000000
0!
1#
0$
0(
0*
1+
01
03
14
#1105000000
1!
1(
11
#1110000000
0!
0(
01
#1115000000
1!
1(
11
#1120000000
0!
0(
01
#1125000000
1!
1(
11
#1130000000
0!
0(
01
#1135000000
1!
1%
1&
1(
1,
1-
10
11
15
16
#1140000000
0!
1$
0(
1*
1,
01
13
15
16
18
#1145000000
1!
0%
0&
b0011 '
1(
0,
0-
b0011 .
b001 /
00
11
05
06
17
#1150000000
0!
0#
0$
0(
0*
0+
01
03
04
#1155000000
1!
1(
11
#1160000000
0!
1#
1$
0(
1*
1+
01
13
14
#1165000000
1!
1(
11
#1170000000
0!
0$
0(
0*
01
03
08
#1175000000
1!
1(
11
07
#1180000000
0!
0#
0(
0+
01
04
#1185000000
1!
1(
11
#1190000000
0!
1#
0(
1+
01
14
#1195000000
1!
1(
11
#1200000000
0!
0(
01
#1205000000
1!
1(
11
#1210000000
0!
1$
0(
1*
01
13
18
#1215000000
1!
1(
11
17
#1220000000
0!
0#
0(
0+
01
04
#1225000000
1!
1(
11
#1230000000
0!
1#
0$
0(
0*
1+
01
03
14
08
#1235000000
1!
1(
11
07
#1240000000
0!
1$
0(
1*
01
13
18
#1245000000
1!
1(
11
17
#1250000000
0!
0#
0$
0(
0*
0+
01
03
04
#1255000000
1!
1(
11
#1260000000
0!
1#
0(
1+
01
14
08
#1265000000
1!
1(
11
07
#1270000000
0!
1$
0(
1*
01
13
18
#1275000000
1!
1(
11
17
#1280000000
0!
0$
0(
0*
01
03
08
#1285000000
1!
1(
11
07
#1290000000
0!
0(
01
#1295000000
1!
1(
11
#1300000000
0!
0(
01
#1305000000
1!
1(
11
#1310000000
0!
0(
01
#1315000000
1!
1(
11
#1320000000
0!
0#
1$
0(
1*
0+
01
13
04
#1325000000
1!
1(
11
#1330000000
0!
1#
0(
1+
01
14
18
#1335000000
1!
1(
11
17
#1340000000
0!
0(
01
#1345000000
1!
1(
11
#1350000000
0!
0#
0(
0+
01
04
#1355000000
1!
1(
11
#1360000000
0!
0(
01
#1365000000
1!
1(
11
#1370000000
0!
1#
0(
1+
01
14
#1375000000
1!
1(
11
#1380000000
0!
0#
0(
0+
01
04
#1385000000
1!
1(
11
#1390000000
0!
1#
0(
1+
01
14
#1395000000
1!
1(
11
#1400000000
0!
0(
01
#1405000000
1!
1&
1(
1-
10
11
16
#1410000000
0!
0$
0(
0*
01
03
16
08
#1415000000
1!
0&
b0110 '
1(
0-
b0110 .
b010 /
00
11
06
07
#1420000000
0!
0(
01
#1425000000
1!
1(
11
#1430000000
0!
0#
1$
0(
1*
0+
01
13
04
#1435000000
1!
1(
11
#1440000000
0!
0(
01
#1445000000
1!
1(
11
#1450000000
0!
1#
0(
1+
01
14
18
#1455000000
1!
1(
11
17
#1460000000
0!
0#
0(
0+
01
04
#1465000000
1!
1(
11
#1470000000
0!
0$
0(
0*
01
03
#1475000000
1!
1(
11
#1480000000
0!
0(
01
#1485000000
1!
1(
11
#1490000000
0!
1#
1$
0(
1*
1+
01
13
14
#1495000000
1!
1(
11
#1500000000
0!
0#
0(
0+
01
04
#1505000000
1!
1(
11
#1510000000
0!
0(
01
#1515000000
1!
1(
11
#1520000000
0!
1#
0$
0(
0*
1+
01
03
14
08
#1525000000
1!
1(
11
07
#1530000000
0!
0#
0(
0+
01
04
#1535000000
1!
1(
11
#1540000000
0!
0(
01
#1545000000
1!
1(
11
#1550000000
0!
1#
0(
1+
01
14
#1555000000
1!
1(
11
#1560000000
0!
0#
0(
0+
01
04
#1565000000
1!
1(
11
#1570000000
0!
0(
01
#1575000000
1!
1(
11
#1580000000
0!
1#
1$
0(
1*
1+
01
13
14
18
#1585000000
1!
1(
11
17
#1590000000
0!
0$
0(
0*
01
03
08
#1595000000
1!
1(
11
07
#1600000000
0!
1$
0(
1*
01
13
18
#1605000000
1!
1(
11
17
#1610000000
0!
0#
0(
0+
01
04
#1615000000
1!
1(
11
#1620000000
0!
1#
0(
1+
01
14
#1625000000
1!
1(
11
#1630000000
0!
0$
0(
0*
01
03
08
#1635000000
1!
1(
11
07
#1640000000
0!
0(
01
#1645000000
1!
1(
11
#1650000000
0!
1$
0(
1*
01
13
18
#1655000000
1!
1(
11
17
#1660000000
0!
0(
01
#1665000000
1!
1(
11
#1670000000
0!
0#
0(
0+
01
04
#1675000000
1!
1(
11
#1680000000
0!
1#
0(
1+
01
14
#1685000000
1!
1(
11
#1690000000
0!
0$
0(
0*
01
03
08
#1695000000
1!
1(
11
07
#1700000000
0!
0(
01
#1705000000
1!
1(
11
#1710000000
0!
0#
1$
0(
1*
0+
01
13
04
#1715000000
1!
1(
11
#1720000000
0!
0(
01
#1725000000
1!
1(
11
#1730000000
0!
1#
0(
1+
01
14
18
#1735000000
1!
1(
11
17
#1740000000
0!
0#
0$
0(
0*
0+
01
03
04
#1745000000
1!
1(
11
#1750000000
0!
1$
0(
1*
01
13
#1755000000
1!
1(
11
#1760000000
0!
0$
0(
0*
01
03
#1765000000
1!
1(
11
#1770000000
0!
1$
0(
1*
01
13
#1775000000
1!
1(
11
#1780000000
0!
1#
0$
0(
0*
1+
01
03
14
08
#1785000000
1!
1(
11
07
#1790000000
0!
0#
1$
0(
1*
0+
01
13
04
#1795000000
1!
1(
11
#1800000000
0!
0(
01
#1805000000
1!
1(
11
#1810000000
0!
1#
0$
0(
0*
1+
01
03
14
#1815000000
1!
1(
11
#1820000000
0!
0#
1$
0(
1*
0+
01
13
04
#1825000000
1!
1(
11
#1830000000
0!
1#
0$
0(
0*
1+
01
03
14
#1835000000
1!
1(
11
#1840000000
0!
0#
1$
0(
1*
0+
01
13
04
#1845000000
1!
1(
11
#1850000000
0!
1#
0$
0(
0*
1+
01
03
14
#1855000000
1!
1(
11
#1860000000
0!
1$
0(
1*
01
13
18
#1865000000
1!
1(
11
17
#1870000000
0!
0$
0(
0*
01
03
08
#1875000000
1!
1(
11
07
#1880000000
0!
0(
01
#1885000000
1!
1(
11
#1890000000
0!
0(
01
#1895000000
1!
1(
11
#1900000000
0!
0#
1$
0(
1*
0+
01
13
04
#1905000000
1!
1(
11
#1910000000
0!
1#
0$
0(
0*
1+
01
03
14
#1915000000
1!
1(
11
#1920000000
0!
1$
0(
1*
01
13
18
#1925000000
1!
1(
11
17
#1930000000
0!
0$
0(
0*
01
03
08
#1935000000
1!
1(
11
07
#1940000000
0!
0#
0(
0+
01
04
#1945000000
1!
1(
11
#1950000000
0!
1#
1$
0(
1*
1+
01
13
14
18
#1955000000
1!
1(
11
17
#1960000000
0!
0#
0(
0+
01
04
#1965000000
1!
1(
11
#1970000000
0!
1#
0$
0(
0*
1+
01
03
14
08
#1975000000
1!
1(
11
07
#1980000000
0!
0#
1$
0(
1*
0+
01
13
04
#1985000000
1!
1(
11
#1990000000
0!
1#
0(
1+
01
14
18
#1995000000
1!
1(
11
17
#2000000000
0!
0#
0(
0+
01
04
#2005000000
1!
1(
11
#2010000000
0!
0(
01
#2015000000
1!
1(
11
#2020000000
0!
1#
0(
1+
01
14
#2025000000
1!
1(
11
#2030000000
0!
0(
01
#2035000000
1!
1(
11
#2040000000
0!
0#
0(
0+
01
04
#2045000000
1!
1(
11
#2050000000
0!
0$
0(
0*
01
03
#2055000000
1!
1(
11
#2060000000
0!
0(
01
#2065000000
1!
1(
11
#2070000000
0!
1$
0(
1*
01
13
#2075000000
1!
1(
11
#2080000000
0!
1#
0(
1+
01
14
#2085000000
1!
1(
11
#2090000000
0!
0#
0$
0(
0*
0+
01
03
04
#2095000000
1!
1(
11
#2100000000
0!
0(
01
#2105000000
1!
1(
11
#2110000000
0!
0(
01
#2115000000
1!
1(
11
#2120000000
0!
0(
01
#2125000000
1!
1(
11
#2130000000
0!
0(
01
#2135000000
1!
1(
11
#2140000000
0!
1#
0(
1+
01
14
08
#2145000000
1!
1(
11
07
#2150000000
0!
1$
0(
1*
01
13
18
#2155000000
1!
1(
11
17
#2160000000
0!
0#
0(
0+
01
04
#2165000000
1!
1(
11
#2170000000
0!
0$
0(
0*
01
03
#2175000000
1!
1(
11
#2180000000
0!
1#
0(
1+
01
14
08
#2185000000
1!
1(
11
07
#2190000000
0!
0#
1$
0(
1*
0+
01
13
04
#2195000000
1!
1(
11
#2200000000
0!
1#
0$
0(
0*
1+
01
03
14
#2205000000
1!
1(
11
#2210000000
0!
0(
01
#2215000000
1!
1(
11
#2220000000
0!
0#
0(
0+
01
04
#2225000000
1!
1(
11
#2230000000
0!
1$
0(
1*
01
13
#2235000000
1!
1(
11
#2240000000
0!
0(
01
#2245000000
1!
1(
11
#2250000000
0!
1#
0$
0(
0*
1+
01
03
14
#2255000000
1!
1(
11
#2260000000
0!
0#
1$
0(
1*
0+
01
13
04
#2265000000
1!
1(
11
#2270000000
0!
1#
0$
0(
0*
1+
01
03
14
#2275000000
1!
1%
1&
1(
1,
1-
10
11
15
16
#2280000000
0!
1$
0(
1*
1,
01
13
15
16
18
#2285000000
1!
0%
0&
b0101 '
1(
0,
0-
b0101 .
b011 /
00
11
05
06
17
#2290000000
0!
0$
0(
0*
01
03
08
#2295000000
1!
1(
11
07
#2300000000
0!
0(
01
#2305000000
1!
1(
11
#2310000000
0!
1$
0(
1*
01
13
18
#2315000000
1!
1(
11
17
#2320000000
0!
0#
0$
0(
0*
0+
01
03
04
#2325000000
1!
1(
11
#2330000000
0!
0(
01
#2335000000
1!
1(
11
#2340000000
0!
1#
0(
1+
01
14
08
#2345000000
1!
1(
11
07
#2350000000
0!
1$
0(
1*
01
13
18
#2355000000
1!
1(
11
17
#2360000000
0!
0#
0(
0+
01
04
#2365000000
1!
1(
11
#2370000000
0!
0$
0(
0*
01
03
#2375000000
1!
1(
11
#2380000000
0!
1$
0(
1*
01
13
#2385000000
1!
1(
11
#2390000000
0!
0(
01
#2395000000
1!
1(
11
#2400000000
0!
1#
0$
0(
0*
1+
01
03
14
08
#2405000000
1!
1(
11
07
#2410000000
0!
0#
0(
0+
01
04
#2415000000
1!
1(
11
#2420000000
0!
1#
0(
1+
01
14
#2425000000
1!
1(
11
#2430000000
0!
1$
0(
1*
01
13
18
#2435000000
1!
1(
11
17
#2440000000
0!
0#
0$
0(
0*
0+
01
03
04
#2445000000
1!
1(
11
#2450000000
0!
1#
1$
0(
1*
1+
01
13
14
#2455000000
1!
1(
11
#2460000000
0!
0#
0$
0(
0*
0+
01
03
04
#2465000000
1!
1(
11
#2470000000
0!
1#
0(
1+
01
14
08
#2475000000
1!
1(
11
07
#2480000000
0!
0#
0(
0+
01
04
#2485000000
1!
1(
11
#2490000000
0!
1$
0(
1*
01
13
#2495000000
1!
1(
11
#2500000000
0!
1#
0(
1+
01
14
18
#2505000000
1!
1(
11
17
#2510000000
0!
0(
01
#2515000000
1!
1(
11
#2520000000
0!
0#
0$
0(
0*
0+
01
03
04
#2525000000
1!
1(
11
#2530000000
0!
1$
0(
1*
01
13
#2535000000
1!
1(
11
#2540000000
0!
1#
0$
0(
0*
1+
01
03
14
08
#2545000000
1!
1(
11
07
#2550000000
0!
0#
0(
0+
01
04
#2555000000
1!
1(
11
#2560000000
0!
0(
01
#2565000000
1!
1(
11
#2570000000
0!
1#
1$
0(
1*
1+
01
13
14
18
#2575000000
1!
1(
11
17
#2580000000
0!
0(
01
#2585000000
1!
1(
11
#2590000000
0!
0$
0(
0*
01
03
08
#2595000000
1!
1(
11
07
#2600000000
0!
0(
01
#2605000000
1!
1(
11
#2610000000
0!
0#
0(
0+
01
04
#2615000000
1!
1(
11
#2620000000
0!
1#
0(
1+
01
14
#2625000000
1!
1(
11
#2630000000
0!
0(
01
#2635000000
1!
1(
11
#2640000000
0!
0#
0(
0+
01
04
#2645000000
1!
1(
11
#2650000000
0!
0(
01
#2655000000
1!
1(
11
#2660000000
0!
1#
1$
0(
1*
1+
01
13
14
18
#2665000000
1!
1(
11
17
#2670000000
0!
0#
0(
0+
01
04
#2675000000
1!
1(
11
#2680000000
0!
1#
0(
1+
01
14
#2685000000
1!
1(
11
#2690000000
0!
0#
0(
0+
01
04
